tinode_grpc/GIT_VERSION
tinode_grpc/__init__.py
tinode_grpc/model_pb2.py
tinode_grpc/model_pb2_grpc.py
tinode_grpc-0.22.3.dist-info/LICENSE
tinode_grpc-0.22.3.dist-info/METADATA
tinode_grpc-0.22.3.dist-info/WHEEL
tinode_grpc-0.22.3.dist-info/top_level.txt
tinode_grpc-0.22.3.dist-info/RECORD
