Metadata-Version: 2.1
Name: tinode-grpc
Version: 0.22.3
Summary: Tinode gRPC bindings.
Home-page: https://github.com/tinode/chat
Author: Tinode Authors
Author-email: info@tinode.co
License: Apache 2.0
Keywords: chat messaging messenger im tinode
Platform: UNKNOWN
Classifier: Programming Language :: Python :: 2
Classifier: Programming Language :: Python :: 2.7
Classifier: Programming Language :: Python :: 3
Classifier: Programming Language :: Python :: 3.5
Classifier: Programming Language :: Python :: 3.6
Classifier: License :: OSI Approved :: Apache Software License
Classifier: Operating System :: OS Independent
Classifier: Topic :: Communications :: Chat
Classifier: Intended Audience :: Developers
License-File: LICENSE
Requires-Dist: protobuf (>=3.6.1)
Requires-Dist: grpcio (>=1.19.0)
